superpose3d/__init__.py
superpose3d-1.5.0.dist-info/LICENSE.md
superpose3d-1.5.0.dist-info/METADATA
superpose3d-1.5.0.dist-info/WHEEL
superpose3d-1.5.0.dist-info/top_level.txt
superpose3d-1.5.0.dist-info/zip-safe
superpose3d-1.5.0.dist-info/RECORD
