Metadata-Version: 2.2
Name: superpose3d
Version: 1.5.0
Summary: Diamond's 1988 rotational superposition algorithm (+scale tranforms)
Home-page: https://github.com/jewettaij/superpose3d
Download-URL: https://github.com/jewettaij/superpose3d/archive/v1.5.0.zip
Author: Andrew Jewett
Author-email: jewett.aij@gmail.com
License: MIT
Keywords: registration,3d,structure-comparison,molecular-structure,clem
Classifier: Development Status :: 5 - Production/Stable
Classifier: License :: OSI Approved :: MIT License
Classifier: Environment :: Console
Classifier: Operating System :: MacOS :: MacOS X
Classifier: Operating System :: POSIX :: Linux
Classifier: Operating System :: Microsoft :: Windows
Classifier: Programming Language :: Python
Classifier: Programming Language :: Python :: 3.5
Classifier: Topic :: Scientific/Engineering
License-File: LICENSE.md
Requires-Dist: numpy
Dynamic: author
Dynamic: author-email
Dynamic: classifier
Dynamic: description
Dynamic: description-content-type
Dynamic: download-url
Dynamic: home-page
Dynamic: keywords
Dynamic: license
Dynamic: requires-dist
Dynamic: summary
